pagodaAL/__init__.py
pagodaAL/zmqclass.py
pagodaAL/zmqreq.py
pagodaAL/zmqsub.py
pagodaal-0.1.0.dist-info/METADATA
pagodaal-0.1.0.dist-info/WHEEL
pagodaal-0.1.0.dist-info/licenses/LICENSE
pagodaal-0.1.0.dist-info/RECORD
