Metadata-Version: 2.4
Name: PagodaAL
Version: 0.1.0
Summary: A ZeroMQ-based communication library.
Project-URL: Homepage, https://github.com/Pagoda-AlphaLee/Pagoda
Project-URL: Bug Tracker, https://github.com/Pagoda-AlphaLee/Pagoda/issues
Author-email: JiajiaLi <jjli2024@niaot.ac.cn>
License-File: LICENSE
Classifier: License :: OSI Approved :: MIT License
Classifier: Operating System :: OS Independent
Classifier: Programming Language :: Python :: 3
Requires-Python: >=3.8
Requires-Dist: pyzmq>=25.0.0
